hi_s00zzang/__init__.py
hi_s00zzang/hello.py
hi_s00zzang-0.7.0.dist-info/METADATA
hi_s00zzang-0.7.0.dist-info/WHEEL
hi_s00zzang-0.7.0.dist-info/entry_points.txt
hi_s00zzang-0.7.0.dist-info/top_level.txt
hi_s00zzang-0.7.0.dist-info/RECORD
