Metadata-Version: 2.1
Name: hi_s00zzang
Version: 0.7.0
Summary: Default template for PDM package
Author-email: S00zzang <sujinpark8719561@gmail.com>
License: MIT
Requires-Python: ==3.12.*
